{
	"name": "giris",
	"layers": [
		{
			"name": "Layer 0",
			"overriden": 0,
			"subLayers": [],
			"instances": [
				{
					"type": "giris",
					"properties": {
						"initially-visible": true,
						"initial-animation": "Animation 1",
						"initial-frame": 0,
						"enable-collisions": true,
						"live-preview": false
					},
					"uid": 2,
					"sid": 283723310858491,
					"tags": "",
					"instanceVariables": {},
					"behaviors": {},
					"showing": true,
					"locked": false,
					"world": {
						"x": 959.947,
						"y": 539.552,
						"width": 1920,
						"height": 1080,
						"originX": 0.5,
						"originY": 0.5,
						"color": [
							1,
							1,
							1,
							1
						],
						"z": 0,
						"angle": 0
					}
				},
				{
					"type": "basla_btn",
					"properties": {
						"initially-visible": true,
						"initial-animation": "Animation 1",
						"initial-frame": 0,
						"enable-collisions": true,
						"live-preview": false
					},
					"uid": 3,
					"sid": 558803018725070,
					"tags": "",
					"instanceVariables": {},
					"behaviors": {},
					"showing": true,
					"locked": false,
					"world": {
						"x": 960,
						"y": 931,
						"width": 422,
						"height": 129,
						"originX": 0.5,
						"originY": 0.5,
						"color": [
							1,
							1,
							1,
							1
						],
						"z": 0,
						"angle": 0
					}
				},
				{
					"type": "bilgi_btn",
					"properties": {
						"initially-visible": true,
						"initial-animation": "Animation 1",
						"initial-frame": 0,
						"enable-collisions": true,
						"live-preview": false
					},
					"uid": 4,
					"sid": 703667061780850,
					"tags": "",
					"instanceVariables": {},
					"behaviors": {},
					"showing": true,
					"locked": false,
					"world": {
						"x": -238,
						"y": 877,
						"width": 322,
						"height": 129,
						"originX": 0.5,
						"originY": 0.5,
						"color": [
							1,
							1,
							1,
							1
						],
						"z": 0,
						"angle": 0
					}
				},
				{
					"type": "anaysayfa_btn",
					"properties": {
						"initially-visible": true,
						"initial-animation": "Animation 1",
						"initial-frame": 0,
						"enable-collisions": true,
						"live-preview": false
					},
					"uid": 25,
					"sid": 706563784146293,
					"tags": "",
					"instanceVariables": {},
					"behaviors": {},
					"showing": true,
					"locked": false,
					"world": {
						"x": 1828,
						"y": 95,
						"width": 109,
						"height": 109,
						"originX": 0.5,
						"originY": 0.5,
						"color": [
							1,
							1,
							1,
							1
						],
						"z": 0,
						"angle": 0
					}
				},
				{
					"type": "tam_ekran_btn",
					"properties": {
						"initially-visible": true,
						"initial-animation": "Animation 1",
						"initial-frame": 0,
						"enable-collisions": true,
						"live-preview": false
					},
					"uid": 26,
					"sid": 236627315777948,
					"tags": "",
					"instanceVariables": {},
					"behaviors": {},
					"showing": true,
					"locked": false,
					"world": {
						"x": 1830,
						"y": 221,
						"width": 109,
						"height": 109,
						"originX": 0.5,
						"originY": 0.5,
						"color": [
							1,
							1,
							1,
							1
						],
						"z": 0,
						"angle": 0
					}
				},
				{
					"type": "ses_ac_btn",
					"properties": {
						"initially-visible": true,
						"initial-animation": "Animation 1",
						"initial-frame": 0,
						"enable-collisions": true,
						"live-preview": false
					},
					"uid": 27,
					"sid": 981583185744249,
					"tags": "",
					"instanceVariables": {},
					"behaviors": {},
					"showing": true,
					"locked": false,
					"world": {
						"x": 1830,
						"y": 347,
						"width": 109,
						"height": 109,
						"originX": 0.5,
						"originY": 0.5,
						"color": [
							1,
							1,
							1,
							1
						],
						"z": 0,
						"angle": 0
					}
				}
			],
			"sid": 514001996527313,
			"effectTypes": [],
			"isInitiallyVisible": true,
			"isInitiallyInteractive": true,
			"isHTMLElementsLayer": false,
			"color": [
				1,
				1,
				1,
				1
			],
			"backgroundColor": [
				0.3686274509803922,
				0.3686274509803922,
				0.3686274509803922,
				1
			],
			"isTransparent": false,
			"sampling": "auto",
			"parallaxX": 1,
			"parallaxY": 1,
			"scaleRate": 1,
			"forceOwnTexture": false,
			"renderingMode": "3d",
			"drawOrder": "z-order",
			"useRenderCells": false,
			"blendMode": "normal",
			"zElevation": 0,
			"global": false
		}
	],
	"sid": 774442692994394,
	"nonworld-instances": [],
	"effectTypes": [],
	"width": 1920,
	"height": 1080,
	"unboundedScrolling": false,
	"sampling": "auto",
	"vpX": 0.5,
	"vpY": 0.5,
	"projection": "perspective",
	"eventSheet": "girisES"
}